Prokhorov_Anton_02/LAB_2_2/top_design.v
// Top design 
module top_design( input [2:0] in, output y, input clk);

    //wire nx1, nx2, nx3; // ~x1, ~x2, ~x3
    wire and1_out, and2_out; // and1: ~X1 & X2 & ~X3  and2: X1 & ~X2 & X3

    //NOT1 INV1(.a(in[2]), .y(nx1), .clk(clk));  // X1
    //NOT1 INV2(.a(in[1]), .y(nx2), .clk(clk));  // X2
    //NOT1 INV3(.a(in[0]), .y(nx3), .clk(clk));  // X3

    // and1: ~X1 & X2 & ~X3
    AND3 AND1( .a(~in[2]), .b(in[1]), .c(~in[0]), .y(and1_out), .clk(clk));

    // and2: X1 & ~X2 & X3
    AND3 AND2(.a(in[2]), .b(~in[1]), .c(in[0]), .y(and2_out), .clk(clk));

    // y = and1_out | and2_out
    OR2 OR1(.a(and1_out), .b(and2_out), .y(y), .clk(clk));

endmodule

// NOT gate
module NOT1(input a, output reg y, input clk);
    always @(posedge clk) begin
        y = ~a;
    end 
endmodule

// AND gate with 3 inputs
module AND3(input a, input b, input c, output reg y, input clk);
    always @(posedge clk) begin
            y <= a & b & c ;
        end
endmodule

// OR gate with 2 inputs
module OR2(input a, input b, output reg y, input clk);
    always @(posedge clk) begin
            y <= a | b; 
        end
endmodule

Prokhorov_Anton_02/LAB_2_2/tb_top_design.v
// Testbench for top_design
module tb_top_design;

    reg [2:0] x;     //  X1, X2, X3
    logic y;         
    logic clk;

  // Instantiate DUT (Device Under Test)
  top_design dut(.in(x), .y(y), .clk(clk));

  initial begin
    clk = 0;
    forever #5 clk = ~clk;
  end
  
  initial begin

    #15;
    x = 3'b000; #11;
    x = 3'b001; #13;
    x = 3'b010; #17;
    x = 3'b011; #14;
    x = 3'b100; #10;
    x = 3'b101; #19;
    x = 3'b110; #11;
    x = 3'b111; #16;
    x = 3'b000; #100;

    $finish;
  end
  initial begin
  
    $monitor("time=%0t | X1=%b X2=%b X3=%b | Y=%b CLK", $time, x[2], x[1], x[0], y, clk);

    
    $dumpfile("wave.vcd");
    $dumpvars(0, tb_top_design);
  end
endmodule

Prokhorov_Anton_02/LAB_2_2/wave.vcd
$date
	Mon Sep 22 21:48:31 2025
$end
$version
	Icarus Verilog
$end
$timescale
	1s
$end
$scope module tb_top_design $end
$var wire 1 ! y $end
$var reg 1 " clk $end
$var reg 3 # x [2:0] $end
$scope module dut $end
$var wire 1 " clk $end
$var wire 3 $ in [2:0] $end
$var wire 1 ! y $end
$var wire 1 % and2_out $end
$var wire 1 & and1_out $end
$scope module AND1 $end
$var wire 1 ' a $end
$var wire 1 ( b $end
$var wire 1 ) c $end
$var wire 1 " clk $end
$var reg 1 & y $end
$upscope $end
$scope module AND2 $end
$var wire 1 * a $end
$var wire 1 + b $end
$var wire 1 , c $end
$var wire 1 " clk $end
$var reg 1 % y $end
$upscope $end
$scope module OR1 $end
$var wire 1 & a $end
$var wire 1 % b $end
$var wire 1 " clk $end
$var reg 1 ! y $end
$upscope $end
$upscope $end
$upscope $end
$enddefinitions $end
$comment Show the parameter values. $end
$dumpall
$end
#0
$dumpvars
x,
x+
x*
x)
x(
x'
x&
x%
bx $
bx #
0"
x!
$end
#5
1"
#10
0"
#15
0%
0&
1'
1)
1+
0(
0*
0,
1"
b0 #
b0 $
#20
0"
#25
0!
1"
#26
0)
1,
b1 #
b1 $
#30
0"
#35
1"
#39
1)
0+
1(
0,
b10 #
b10 $
#40
0"
#45
1&
1"
#50
0"
#55
1!
1"
#56
0)
1,
b11 #
b11 $
#60
0"
#65
0&
1"
#70
0'
1)
1+
0(
1*
0,
0"
b100 #
b100 $
#75
0!
1"
#80
0)
1,
0"
b101 #
b101 $
#85
1%
1"
#90
0"
#95
1!
1"
#99
1)
0+
1(
0,
b110 #
b110 $
#100
0"
#105
0%
1"
#110
0)
1,
0"
b111 #
b111 $
#115
0!
1"
#120
0"
#125
1"
#126
1'
1)
1+
0(
0*
0,
b0 #
b0 $
