Prokhorov_Anton_Verilog_01/n_bit_shift_register/shift_reg.v
module shift_reg  #(parameter MSB=8) (  
            input d,                      // Declare input for data to the first flop in the shift register
            input clk,                    // Declare input for clock to all flops in the shift register
            input en,                     // Declare input for enable to switch the shift register on/off
            input dir,                    // Declare input to shift in either left or right direction
            input rstn,                   // Declare input to reset the register to a default value
            output reg [MSB-1:0] out);    // Declare output to read out the current value of all flops in this register


   // This always block will "always" be triggered on the rising edge of clock
   // Once it enters the block, it will first check to see if reset is 0 and if yes then reset register
   // If no, then check to see if the shift register is enabled
   // If no => maintain previous output. If yes, then shift based on the requested direction
   always @ (posedge clk)
      if (!rstn)
         out <= 0;
      else begin
         if (en)
            case (dir) 
               0 :  out <= {out[MSB-2:0], d};
               1 :  out <= {d, out[MSB-1:1]};
            endcase
         else
            out <= out;
      end
endmodule

Prokhorov_Anton_Verilog_01/n_bit_shift_register/tb_shift_reg.v
module tb_sr;

   parameter MSB = 16;        // [Optional] Declare a parameter to represent number of bits in shift register

   reg data;                  // Declare a variable to drive d-input of design
   reg clk;                   // Declare a variable to drive clock to the design
   reg en;                    // Declare a variable to drive enable to the design
   reg dir;                   // Declare a variable to drive direction of shift registe
   reg rstn;                  // Declare a variable to drive reset to the design
   wire [MSB-1:0] out;        // Declare a wire to capture output from the design

   // Instantiate design (16-bit shift register) by passing MSB and connect with TB signals
   shift_reg  #(MSB) sr0  (  .d (data),
                             .clk (clk),
                             .en (en),
                             .dir (dir),
                             .rstn (rstn),
                             .out (out));

   // Generate clock time period = 20ns, freq => 50MHz
   always #10 clk = ~clk;

   // Initialize variables to default values at time 0
   initial begin
      clk <= 0;
      en <= 0;
      dir <= 0;
      rstn <= 0;
      data <= 'h1;
   end

   // Drive main stimulus to the design to verify if this works
   initial begin

      // 1. Apply reset and deassert reset after some time
      rstn <= 0;
      #20 rstn <= 1;
          en <= 1;

	  // 2. For 7 clocks, drive alternate values to data pin
      repeat (7) @ (posedge clk)
         data <= ~data;

     // 4. Shift direction and drive alternate value to data pin for another 7 clocks
      #10 dir <= 1;
      repeat (7) @ (posedge clk)
         data <= ~data;

      // 5. Drive nothing for next 7 clocks, allow shift register to simply shift based on dir
      repeat (7) @ (posedge clk);

      // 6. Finish the simulation
      $finish;
   end

   // Monitor values of these variables and print them into the logfile for debug
   initial begin
      $monitor ("rstn=%0b data=%b, en=%0b, dir=%0b, out=%b", rstn, data, en, dir, out);
      $dumpfile("wave.vcd");
      
      $dumpvars(0, tb_sr);
   end
endmodule

Prokhorov_Anton_Verilog_01/n_bit_shift_register/wave.vcd
$date
	Tue Aug 12 19:48:57 2025
$end
$version
	Icarus Verilog
$end
$timescale
	1s
$end
$scope module tb_sr $end
$var wire 16 ! out [15:0] $end
$var reg 1 " clk $end
$var reg 1 # data $end
$var reg 1 $ dir $end
$var reg 1 % en $end
$var reg 1 & rstn $end
$scope module sr0 $end
$var wire 1 " clk $end
$var wire 1 # d $end
$var wire 1 $ dir $end
$var wire 1 % en $end
$var wire 1 & rstn $end
$var reg 16 ' out [15:0] $end
$upscope $end
$upscope $end
$enddefinitions $end
#0
$dumpvars
bx '
0&
0%
0$
1#
0"
bx !
$end
#10
b0 !
b0 '
1"
#20
1%
1&
0"
#30
b1 !
b1 '
0#
1"
#40
0"
#50
1#
b10 !
b10 '
1"
#60
0"
#70
b101 !
b101 '
0#
1"
#80
0"
#90
1#
b1010 !
b1010 '
1"
#100
0"
#110
b10101 !
b10101 '
0#
1"
#120
0"
#130
1#
b101010 !
b101010 '
1"
#140
0"
#150
b1010101 !
b1010101 '
0#
1"
#160
1$
0"
#170
b101010 !
b101010 '
1#
1"
#180
0"
#190
0#
b1000000000010101 !
b1000000000010101 '
1"
#200
0"
#210
b100000000001010 !
b100000000001010 '
1#
1"
#220
0"
#230
0#
b1010000000000101 !
b1010000000000101 '
1"
#240
0"
#250
b101000000000010 !
b101000000000010 '
1#
1"
#260
0"
#270
0#
b1010100000000001 !
b1010100000000001 '
1"
#280
0"
#290
b101010000000000 !
b101010000000000 '
1#
1"
#300
0"
#310
b1010101000000000 !
b1010101000000000 '
1"
#320
0"
#330
b1101010100000000 !
b1101010100000000 '
1"
#340
0"
#350
b1110101010000000 !
b1110101010000000 '
1"
#360
0"
#370
b1111010101000000 !
b1111010101000000 '
1"
#380
0"
#390
b1111101010100000 !
b1111101010100000 '
1"
#400
0"
#410
b1111110101010000 !
b1111110101010000 '
1"
#420
0"
#430
b1111111010101000 !
b1111111010101000 '
1"
