Prokhorov_Anton_02/LAB_2_1/top_design.v
module top_design(input [2:0] in, output y);

    wire and1_out, and2_out; // and1: ~X1 & X2 & ~X3  and2: X1 & ~X2 & X3
    // and1: ~X1 & X2 & ~X3
    AND3 AND1( .a(~in[2]), .b(in[1]), .c(~in[0]), .y(and1_out));
    // and2: X1 & ~X2 & X3
    AND3 AND2(.a(in[2]), .b(~in[1]), .c(in[0]), .y(and2_out));
    // y = and1_out | and2_out
    OR2 OR1(.a(and1_out), .b(and2_out), .y(y));

endmodule

// NOT gate
module NOT1(input a, output y);
        assign y = ~a;
endmodule

// AND gate with 3 inputs
module AND3(input a, input b, input c, output y);
        assign y = a & b & c;
endmodule

// OR gate with 2 inputs
module OR2(input a, input b, output y);
        assign y = a | b; 
endmodule

Prokhorov_Anton_02/LAB_2_1/tb_top_design.v
module tb_top_design;

    reg [2:0] x;  //  X1, X2, X3
    logic y;          
  // Instantiate DUT (Device Under Test)
  top_design dut(.in(x), .y(y));

  initial begin

    x = 3'b000; #10;
    x = 3'b001; #10;
    x = 3'b010; #10;
    x = 3'b011; #10;
    x = 3'b100; #10;
    x = 3'b101; #10;
    x = 3'b110; #10;
    x = 3'b111; #10;
    $finish;

  end

  initial begin
    $monitor("time=%0t | X1=%b X2=%b X3=%b | Y=%b CLK", $time, x[2], x[1], x[0], y);
    $dumpfile("wave.vcd");
    $dumpvars(0, tb_top_design);
  end

endmodule

Prokhorov_Anton_02/LAB_2_1/wave.vcd
$date
	Mon Sep 22 19:42:44 2025
$end
$version
	Icarus Verilog
$end
$timescale
	1s
$end
$scope module tb_top_design $end
$var wire 1 ! y $end
$var reg 3 " x [2:0] $end
$scope module dut $end
$var wire 3 # in [2:0] $end
$var wire 1 ! y $end
$var wire 1 $ and2_out $end
$var wire 1 % and1_out $end
$scope module AND1 $end
$var wire 1 & a $end
$var wire 1 ' b $end
$var wire 1 ( c $end
$var wire 1 % y $end
$upscope $end
$scope module AND2 $end
$var wire 1 ) a $end
$var wire 1 * b $end
$var wire 1 + c $end
$var wire 1 $ y $end
$upscope $end
$scope module OR1 $end
$var wire 1 % a $end
$var wire 1 $ b $end
$var wire 1 ! y $end
$upscope $end
$upscope $end
$upscope $end
$enddefinitions $end
$comment Show the parameter values. $end
$dumpall
$end
#0
$dumpvars
0+
1*
0)
1(
0'
1&
0%
0$
b0 #
b0 "
0!
$end
#10
0(
1+
b1 "
b1 #
#20
1!
1%
1(
0*
1'
0+
b10 "
b10 #
#30
0!
0%
0(
1+
b11 "
b11 #
#40
0&
1(
1*
0'
1)
0+
b100 "
b100 #
#50
1!
0(
1$
1+
b101 "
b101 #
#60
0!
1(
0*
0$
1'
0+
b110 "
b110 #
#70
0(
1+
b111 "
b111 #
